{
  "code": "600522",
  "name": "中天科技",
  "rows": [
    {
      "date": "2026-04-01",
      "open": 30.99,
      "close": 29.16,
      "high": 30.99,
      "low": 28.6,
      "volume": 158760715.0,
      "amount": 4628127275.0,
      "change_pct": null,
      "turnover": 4.651715706001279,
      "float_market_cap": 99521611852.32,
      "pe_dynamic": 34.73142176
    },
    {
      "date": "2026-04-02",
      "open": 29.15,
      "close": 29.32,
      "high": 30.62,
      "low": 29.11,
      "volume": 142711659.0,
      "amount": 4241717845.0,
      "change_pct": null,
      "turnover": 4.181475660397465,
      "float_market_cap": 100067683796.64,
      "pe_dynamic": 34.92199198
    },
    {
      "date": "2026-04-03",
      "open": 29.46,
      "close": 30.67,
      "high": 31.5,
      "low": 29.25,
      "volume": 196398921.0,
      "amount": 6023713621.0,
      "change_pct": null,
      "turnover": 5.75452148510042,
      "float_market_cap": 104675165826.84,
      "pe_dynamic": 36.52992817
    },
    {
      "date": "2026-04-07",
      "open": 30.82,
      "close": 30.25,
      "high": 31.77,
      "low": 30.06,
      "volume": 149996542.0,
      "amount": 4611949230.0,
      "change_pct": null,
      "turnover": 4.394923960044401,
      "float_market_cap": 103241726973.0,
      "pe_dynamic": 36.02968135
    },
    {
      "date": "2026-04-08",
      "open": 30.98,
      "close": 30.7,
      "high": 31.17,
      "low": 29.5,
      "volume": 191684462.0,
      "amount": 5787770563.0,
      "change_pct": null,
      "turnover": 5.616387041856075,
      "float_market_cap": 104777554316.4,
      "pe_dynamic": 36.56566008
    },
    {
      "date": "2026-04-09",
      "open": 30.28,
      "close": 31.4,
      "high": 32.18,
      "low": 29.41,
      "volume": 222298172.0,
      "amount": 6900041051.0,
      "change_pct": null,
      "turnover": 6.513373904292216,
      "float_market_cap": 107166619072.8,
      "pe_dynamic": 37.39940478
    },
    {
      "date": "2026-04-10",
      "open": 31.38,
      "close": 29.8,
      "high": 31.4,
      "low": 29.5,
      "volume": 257551674.0,
      "amount": 7780832324.0,
      "change_pct": null,
      "turnover": 7.54630745428881,
      "float_market_cap": 101705899629.6,
      "pe_dynamic": 35.49370262
    },
    {
      "date": "2026-04-13",
      "open": 29.41,
      "close": 28.52,
      "high": 29.63,
      "low": 28.33,
      "volume": 216733487.0,
      "amount": 6214379523.0,
      "change_pct": null,
      "turnover": 6.350327695956295,
      "float_market_cap": 97337324075.04,
      "pe_dynamic": 33.9691409
    },
    {
      "date": "2026-04-14",
      "open": 28.8,
      "close": 28.33,
      "high": 29.42,
      "low": 27.88,
      "volume": 172196796.0,
      "amount": 4918901633.0,
      "change_pct": null,
      "turnover": 5.045395143731232,
      "float_market_cap": 96688863641.16,
      "pe_dynamic": 33.74283877
    },
    {
      "date": "2026-04-15",
      "open": 28.26,
      "close": 27.8,
      "high": 29.14,
      "low": 27.68,
      "volume": 156296595.0,
      "amount": 4429742642.0,
      "change_pct": null,
      "turnover": 4.579516574714475,
      "float_market_cap": 94880000325.6,
      "pe_dynamic": 33.11157493
    },
    {
      "date": "2026-04-16",
      "open": 27.81,
      "close": 28.0,
      "high": 28.33,
      "low": 27.42,
      "volume": 128820809.0,
      "amount": 3599850270.0,
      "change_pct": null,
      "turnover": 3.774471414323694,
      "float_market_cap": 95562590256.0,
      "pe_dynamic": 33.3497877
    },
    {
      "date": "2026-04-17",
      "open": 28.01,
      "close": 28.14,
      "high": 28.5,
      "low": 27.62,
      "volume": 160528176.0,
      "amount": 4497406059.0,
      "change_pct": null,
      "turnover": 4.703502611177694,
      "float_market_cap": 96040403207.28,
      "pe_dynamic": 33.51653664
    },
    {
      "date": "2026-04-20",
      "open": 28.9,
      "close": 30.95,
      "high": 30.95,
      "low": 28.83,
      "volume": 224783834.0,
      "amount": 6813994827.0,
      "change_pct": null,
      "turnover": 6.586204219809569,
      "float_market_cap": 105630791729.4,
      "pe_dynamic": 36.86342605
    },
    {
      "date": "2026-04-21",
      "open": 31.0,
      "close": 32.44,
      "high": 32.88,
      "low": 30.78,
      "volume": 395727458.0,
      "amount": 12540542961.0,
      "change_pct": null,
      "turnover": 11.59488121273932,
      "float_market_cap": 110716086710.88,
      "pe_dynamic": 38.63811118
    },
    {
      "date": "2026-04-22",
      "open": 32.54,
      "close": 34.82,
      "high": 34.84,
      "low": 32.5,
      "volume": 300397247.0,
      "amount": 10225640327.0,
      "change_pct": null,
      "turnover": 8.801689964103812,
      "float_market_cap": 118838906882.64,
      "pe_dynamic": 41.47284313
    },
    {
      "date": "2026-04-23",
      "open": 34.0,
      "close": 34.07,
      "high": 35.04,
      "low": 33.2,
      "volume": 285776244.0,
      "amount": 9725410049.0,
      "change_pct": null,
      "turnover": 8.37329211207479,
      "float_market_cap": 116279194643.64,
      "pe_dynamic": 40.57954525
    },
    {
      "date": "2026-04-24",
      "open": 34.0,
      "close": 33.21,
      "high": 34.5,
      "low": 32.58,
      "volume": 209921085.0,
      "amount": 7002735957.0,
      "change_pct": null,
      "turnover": 6.150723169238243,
      "float_market_cap": 113344057942.92,
      "pe_dynamic": 39.55523034
    },
    {
      "date": "2026-04-27",
      "open": 34.29,
      "close": 35.78,
      "high": 36.53,
      "low": 34.23,
      "volume": 339355803.0,
      "amount": 12223484606.0,
      "change_pct": null,
      "turnover": 9.943182220726179,
      "float_market_cap": 122115338548.56,
      "pe_dynamic": 38.23710379
    },
    {
      "date": "2026-04-28",
      "open": 35.78,
      "close": 35.0,
      "high": 36.46,
      "low": 34.0,
      "volume": 264772903.0,
      "amount": 9259501435.0,
      "change_pct": null,
      "turnover": 7.757890681007913,
      "float_market_cap": 119453237820.0,
      "pe_dynamic": 37.4035392
    },
    {
      "date": "2026-04-29",
      "open": 34.2,
      "close": 34.28,
      "high": 34.49,
      "low": 33.33,
      "volume": 178421740.0,
      "amount": 6066232868.0,
      "change_pct": null,
      "turnover": 5.227787052042923,
      "float_market_cap": 116995914070.56,
      "pe_dynamic": 36.63409496
    },
    {
      "date": "2026-04-30",
      "open": 34.3,
      "close": 33.12,
      "high": 34.35,
      "low": 32.51,
      "volume": 212348781.0,
      "amount": 7032576728.0,
      "change_pct": null,
      "turnover": 6.221855071186383,
      "float_market_cap": 113036892474.24,
      "pe_dynamic": 35.39443481
    },
    {
      "date": "2026-05-06",
      "open": 33.67,
      "close": 34.89,
      "high": 35.25,
      "low": 33.67,
      "volume": 234412095.0,
      "amount": 8128161194.0,
      "change_pct": null,
      "turnover": 6.868313889794235,
      "float_market_cap": 119077813358.28,
      "pe_dynamic": 37.28598522
    },
    {
      "date": "2026-05-07",
      "open": 36.1,
      "close": 38.38,
      "high": 38.38,
      "low": 35.0,
      "volume": 289108056.0,
      "amount": 10604649063.0,
      "change_pct": null,
      "turnover": 8.470914765196778,
      "float_market_cap": 130989007643.76,
      "pe_dynamic": 41.01565241
    },
    {
      "date": "2026-05-08",
      "open": 38.2,
      "close": 40.9,
      "high": 41.16,
      "low": 38.2,
      "volume": 312118083.0,
      "amount": 12449499866.0,
      "change_pct": null,
      "turnover": 9.145112434257499,
      "float_market_cap": 139589640766.8,
      "pe_dynamic": 43.70870723
    },
    {
      "date": "2026-05-11",
      "open": 44.98,
      "close": 43.86,
      "high": 44.99,
      "low": 42.75,
      "volume": 414883202.0,
      "amount": 18293626375.0,
      "change_pct": null,
      "turnover": 12.156147740324181,
      "float_market_cap": 149691971736.72,
      "pe_dynamic": 46.87197798
    },
    {
      "date": "2026-05-12",
      "open": 44.0,
      "close": 44.08,
      "high": 46.18,
      "low": 43.25,
      "volume": 428131082.0,
      "amount": 18959969316.0,
      "change_pct": null,
      "turnover": 12.544312857035958,
      "float_market_cap": 150442820660.16,
      "pe_dynamic": 47.10708594
    },
    {
      "date": "2026-05-13",
      "open": 42.54,
      "close": 43.6,
      "high": 43.94,
      "low": 42.54,
      "volume": 285206687.0,
      "amount": 12372512167.0,
      "change_pct": null,
      "turnover": 8.356603995985347,
      "float_market_cap": 148804604827.2,
      "pe_dynamic": 46.59412311
    },
    {
      "date": "2026-05-14",
      "open": 44.5,
      "close": 44.1,
      "high": 45.96,
      "low": 43.68,
      "volume": 374586767.0,
      "amount": 16746144055.0,
      "change_pct": null,
      "turnover": 10.975455403524364,
      "float_market_cap": 150511079653.2,
      "pe_dynamic": 47.12845939
    },
    {
      "date": "2026-05-15",
      "open": 44.38,
      "close": 40.99,
      "high": 44.9,
      "low": 40.11,
      "volume": 365149238.0,
      "amount": 15238467566.0,
      "change_pct": null,
      "turnover": 10.698934213284433,
      "float_market_cap": 139896806235.48,
      "pe_dynamic": 43.80488776
    },
    {
      "date": "2026-05-18",
      "open": 41.9,
      "close": 43.95,
      "high": 44.68,
      "low": 41.9,
      "volume": 326211607.0,
      "amount": 14221251074.0,
      "change_pct": null,
      "turnover": 9.55805506268863,
      "float_market_cap": 149999137205.4,
      "pe_dynamic": 46.96815851
    },
    {
      "date": "2026-05-19",
      "open": 43.0,
      "close": 44.55,
      "high": 44.9,
      "low": 41.29,
      "volume": 319664725.0,
      "amount": 13791413028.0,
      "change_pct": null,
      "turnover": 9.366230316719598,
      "float_market_cap": 152046906996.6,
      "pe_dynamic": 47.60936204
    },
    {
      "date": "2026-05-20",
      "open": 44.55,
      "close": 45.41,
      "high": 47.4,
      "low": 43.8,
      "volume": 339723015.0,
      "amount": 15540068886.0,
      "change_pct": null,
      "turnover": 9.953941594213708,
      "float_market_cap": 154982043697.32,
      "pe_dynamic": 48.52842043
    },
    {
      "date": "2026-05-21",
      "open": 45.0,
      "close": 41.9,
      "high": 45.77,
      "low": 41.85,
      "volume": 308539800.0,
      "amount": 13419587018.0,
      "change_pct": null,
      "turnover": 9.040268139296888,
      "float_market_cap": 143002590418.8,
      "pe_dynamic": 44.77737978
    },
    {
      "date": "2026-05-22",
      "open": 42.69,
      "close": 43.82,
      "high": 43.88,
      "low": 42.48,
      "volume": 226491466.0,
      "amount": 9819713358.0,
      "change_pct": null,
      "turnover": 6.636238125202791,
      "float_market_cap": 149555453750.64,
      "pe_dynamic": 46.82923107
    },
    {
      "date": "2026-05-25",
      "open": 44.29,
      "close": 42.89,
      "high": 44.66,
      "low": 41.8,
      "volume": 280949630.0,
      "amount": 11914000728.0,
      "change_pct": null,
      "turnover": 8.231871508428569,
      "float_market_cap": 146381410574.28,
      "pe_dynamic": 45.8353656
    },
    {
      "date": "2026-05-26",
      "open": 42.0,
      "close": 40.48,
      "high": 42.05,
      "low": 39.26,
      "volume": 293174055.0,
      "amount": 11881584952.0,
      "change_pct": null,
      "turnover": 8.590049221153878,
      "float_market_cap": 138156201912.96,
      "pe_dynamic": 43.25986476
    },
    {
      "date": "2026-05-27",
      "open": 39.8,
      "close": 39.05,
      "high": 40.9,
      "low": 38.82,
      "volume": 222174791.0,
      "amount": 8834663451.0,
      "change_pct": null,
      "turnover": 6.509758820198383,
      "float_market_cap": 133275683910.6,
      "pe_dynamic": 41.73166302
    },
    {
      "date": "2026-05-28",
      "open": 39.25,
      "close": 40.52,
      "high": 40.74,
      "low": 37.75,
      "volume": 240048858.0,
      "amount": 9439684920.0,
      "change_pct": null,
      "turnover": 7.033471995677715,
      "float_market_cap": 138292719899.04,
      "pe_dynamic": 43.30261166
    },
    {
      "date": "2026-05-29",
      "open": 41.0,
      "close": 42.19,
      "high": 43.6,
      "low": 38.85,
      "volume": 385229968.0,
      "amount": 16015134833.0,
      "change_pct": null,
      "turnover": 11.287302986560436,
      "float_market_cap": 143992345817.88,
      "pe_dynamic": 45.08729482
    },
    {
      "date": "2026-06-01",
      "open": 42.0,
      "close": 39.39,
      "high": 42.15,
      "low": 39.07,
      "volume": 246232465.0,
      "amount": 9947637680.0,
      "change_pct": null,
      "turnover": 7.214652722922735,
      "float_market_cap": 134436086792.28,
      "pe_dynamic": 42.09501169
    },
    {
      "date": "2026-06-02",
      "open": 39.03,
      "close": 42.89,
      "high": 43.33,
      "low": 39.03,
      "volume": 405978244.0,
      "amount": 17069390712.0,
      "change_pct": null,
      "turnover": 11.895230970140313,
      "float_market_cap": 146381410574.28,
      "pe_dynamic": 45.8353656
    },
    {
      "date": "2026-06-03",
      "open": 43.89,
      "close": 44.98,
      "high": 46.98,
      "low": 43.4,
      "volume": 419182256.0,
      "amount": 18962761947.0,
      "change_pct": null,
      "turnover": 12.28211074705886,
      "float_market_cap": 153514475346.96,
      "pe_dynamic": 48.06889123
    },
    {
      "date": "2026-06-04",
      "open": 43.81,
      "close": 46.06,
      "high": 47.18,
      "low": 43.81,
      "volume": 354368175.0,
      "amount": 16274195947.0,
      "change_pct": null,
      "turnover": 10.383047250413995,
      "float_market_cap": 157200460971.12,
      "pe_dynamic": 49.22305758
    },
    {
      "date": "2026-06-05",
      "open": 45.08,
      "close": 46.07,
      "high": 49.37,
      "low": 44.95,
      "volume": 406564804.0,
      "amount": 19200932659.0,
      "change_pct": null,
      "turnover": 11.91241727699533,
      "float_market_cap": 157234590467.64,
      "pe_dynamic": 49.23374431
    },
    {
      "date": "2026-06-08",
      "open": 44.0,
      "close": 49.53,
      "high": 50.68,
      "low": 44.0,
      "volume": 513156539.0,
      "amount": 25205130127.0,
      "change_pct": null,
      "turnover": 15.035573076775059,
      "float_market_cap": 169043396263.56,
      "pe_dynamic": 52.93135133
    },
    {
      "date": "2026-06-09",
      "open": 50.53,
      "close": 54.48,
      "high": 54.48,
      "low": 48.56,
      "volume": 484808226.0,
      "amount": 24977886012.0,
      "change_pct": null,
      "turnover": 14.204962728234232,
      "float_market_cap": 185937497040.96,
      "pe_dynamic": 58.22128044
    },
    {
      "date": "2026-06-10",
      "open": 52.5,
      "close": 50.2,
      "high": 53.79,
      "low": 49.18,
      "volume": 383672432.0,
      "amount": 19561624115.0,
      "change_pct": null,
      "turnover": 11.24166691926342,
      "float_market_cap": 171330072530.4,
      "pe_dynamic": 53.64736193
    },
    {
      "date": "2026-06-11",
      "open": 49.69,
      "close": 49.27,
      "high": 51.0,
      "low": 48.05,
      "volume": 289909172.0,
      "amount": 14363164879.0,
      "change_pct": null,
      "turnover": 8.494387599011672,
      "float_market_cap": 168156029354.04,
      "pe_dynamic": 52.65349646
    },
    {
      "date": "2026-06-12",
      "open": 50.72,
      "close": 48.6,
      "high": 52.2,
      "low": 48.59,
      "volume": 330123533.0,
      "amount": 16532537299.0,
      "change_pct": null,
      "turnover": 9.672675153779268,
      "float_market_cap": 165869353087.2,
      "pe_dynamic": 51.93748586
    },
    {
      "date": "2026-06-15",
      "open": 49.97,
      "close": 51.35,
      "high": 51.47,
      "low": 46.88,
      "volume": 309924242.0,
      "amount": 15423309740.0,
      "change_pct": null,
      "turnover": 9.080832523221764,
      "float_market_cap": 175254964630.2,
      "pe_dynamic": 54.87633537
    },
    {
      "date": "2026-06-16",
      "open": 51.4,
      "close": 54.15,
      "high": 55.16,
      "low": 51.0,
      "volume": 317582170.0,
      "amount": 17060543680.0,
      "change_pct": null,
      "turnover": 9.305211104239284,
      "float_market_cap": 184811223655.8,
      "pe_dynamic": 57.8686185
    },
    {
      "date": "2026-06-17",
      "open": 52.65,
      "close": 54.91,
      "high": 56.32,
      "low": 52.63,
      "volume": 309659027.0,
      "amount": 16944144744.0,
      "change_pct": null,
      "turnover": 9.073061679024146,
      "float_market_cap": 187405065391.32,
      "pe_dynamic": 58.68080964
    },
    {
      "date": "2026-06-18",
      "open": 54.13,
      "close": 56.55,
      "high": 57.77,
      "low": 54.13,
      "volume": 284626347.0,
      "amount": 16052977965.0,
      "change_pct": null,
      "turnover": 8.339599936178606,
      "float_market_cap": 193002302820.6,
      "pe_dynamic": 60.43343262
    },
    {
      "date": "2026-06-22",
      "open": 58.38,
      "close": 59.63,
      "high": 61.18,
      "low": 57.57,
      "volume": 299380164.0,
      "amount": 17763185299.0,
      "change_pct": null,
      "turnover": 8.771889260791239,
      "float_market_cap": 203514187748.76,
      "pe_dynamic": 63.72494407
    },
    {
      "date": "2026-06-23",
      "open": 60.3,
      "close": 61.73,
      "high": 64.64,
      "low": 58.47,
      "volume": 323977914.0,
      "amount": 19967570899.0,
      "change_pct": null,
      "turnover": 9.4926074813365,
      "float_market_cap": 210681382017.96,
      "pe_dynamic": 65.96915642
    },
    {
      "date": "2026-06-24",
      "open": 60.0,
      "close": 61.91,
      "high": 63.99,
      "low": 59.8,
      "volume": 299112355.0,
      "amount": 18535356007.0,
      "change_pct": null,
      "turnover": 8.764042411956448,
      "float_market_cap": 211295712955.32,
      "pe_dynamic": 66.16151748
    },
    {
      "date": "2026-06-25",
      "open": 63.4,
      "close": 68.1,
      "high": 68.1,
      "low": 61.81,
      "volume": 316083276.0,
      "amount": 20865549415.0,
      "change_pct": null,
      "turnover": 9.26129325742541,
      "float_market_cap": 232421871301.2,
      "pe_dynamic": 72.77660055
    },
    {
      "date": "2026-06-26",
      "open": 65.66,
      "close": 61.29,
      "high": 66.48,
      "low": 61.29,
      "volume": 395453043.0,
      "amount": 24899112998.0,
      "change_pct": null,
      "turnover": 11.586840806991196,
      "float_market_cap": 209179684171.08,
      "pe_dynamic": 65.4989405
    },
    {
      "date": "2026-06-29",
      "open": 60.0,
      "close": 58.84,
      "high": 62.26,
      "low": 56.39,
      "volume": 319212262.0,
      "amount": 18850851602.0,
      "change_pct": null,
      "turnover": 9.352973074564417,
      "float_market_cap": 200817957523.68,
      "pe_dynamic": 62.88069275
    },
    {
      "date": "2026-06-30",
      "open": 59.81,
      "close": 60.68,
      "high": 61.5,
      "low": 58.05,
      "volume": 251737711.0,
      "amount": 15070116615.0,
      "change_pct": null,
      "turnover": 7.375957358541192,
      "float_market_cap": 207097784883.36,
      "pe_dynamic": 64.84705024
    }
  ]
}