{
  "code": "600367",
  "name": "红星发展",
  "rows": [
    {
      "date": "2026-04-01",
      "open": 20.88,
      "close": 20.62,
      "high": 21.19,
      "low": 20.5,
      "volume": 25967114.0,
      "amount": 538910156.0,
      "change_pct": null,
      "turnover": 8.06499281669987,
      "float_market_cap": 6639087012.84,
      "pe_dynamic": 50.61749432
    },
    {
      "date": "2026-04-02",
      "open": 20.62,
      "close": 20.63,
      "high": 21.08,
      "low": 20.33,
      "volume": 22103967.0,
      "amount": 458689054.0,
      "change_pct": null,
      "turnover": 6.865157794415312,
      "float_market_cap": 6642306744.66,
      "pe_dynamic": 50.64204208
    },
    {
      "date": "2026-04-03",
      "open": 20.55,
      "close": 19.64,
      "high": 20.63,
      "low": 19.61,
      "volume": 23093324.0,
      "amount": 459496340.0,
      "change_pct": null,
      "turnover": 7.17243711310093,
      "float_market_cap": 6323553294.48,
      "pe_dynamic": 48.21181321
    },
    {
      "date": "2026-04-07",
      "open": 19.8,
      "close": 20.33,
      "high": 20.37,
      "low": 19.7,
      "volume": 19533868.0,
      "amount": 392652064.0,
      "change_pct": null,
      "turnover": 6.0669239216327036,
      "float_market_cap": 6545714790.06,
      "pe_dynamic": 49.90560909
    },
    {
      "date": "2026-04-08",
      "open": 19.88,
      "close": 20.4,
      "high": 20.46,
      "low": 19.44,
      "volume": 27822835.0,
      "amount": 560230293.0,
      "change_pct": null,
      "turnover": 8.641351688725429,
      "float_market_cap": 6568252912.8,
      "pe_dynamic": 50.07744346
    },
    {
      "date": "2026-04-09",
      "open": 20.29,
      "close": 20.7,
      "high": 20.76,
      "low": 20.08,
      "volume": 25852965.0,
      "amount": 529266664.0,
      "change_pct": null,
      "turnover": 8.02953986397538,
      "float_market_cap": 6664844867.4,
      "pe_dynamic": 50.81387645
    },
    {
      "date": "2026-04-10",
      "open": 20.7,
      "close": 20.38,
      "high": 20.77,
      "low": 20.25,
      "volume": 22170385.0,
      "amount": 454006558.0,
      "change_pct": null,
      "turnover": 6.885786220543051,
      "float_market_cap": 6561813449.16,
      "pe_dynamic": 50.02834792
    },
    {
      "date": "2026-04-13",
      "open": 20.78,
      "close": 21.53,
      "high": 21.99,
      "low": 20.41,
      "volume": 46871387.0,
      "amount": 990933748.0,
      "change_pct": null,
      "turnover": 14.557543801893413,
      "float_market_cap": 6932082608.46,
      "pe_dynamic": 52.85134106
    },
    {
      "date": "2026-04-14",
      "open": 20.8,
      "close": 21.01,
      "high": 21.11,
      "low": 20.76,
      "volume": 32279035.0,
      "amount": 673900115.0,
      "change_pct": null,
      "turnover": 10.025380001990353,
      "float_market_cap": 6764656553.82,
      "pe_dynamic": 51.57485721
    },
    {
      "date": "2026-04-15",
      "open": 20.93,
      "close": 20.23,
      "high": 21.0,
      "low": 20.18,
      "volume": 25948479.0,
      "amount": 531198390.0,
      "change_pct": null,
      "turnover": 8.059205067582306,
      "float_market_cap": 6513517471.86,
      "pe_dynamic": 49.66013143
    },
    {
      "date": "2026-04-16",
      "open": 20.23,
      "close": 21.28,
      "high": 21.36,
      "low": 20.2,
      "volume": 35121194.0,
      "amount": 735244792.0,
      "change_pct": null,
      "turnover": 10.908111595455798,
      "float_market_cap": 6851589312.96,
      "pe_dynamic": 52.2376469
    },
    {
      "date": "2026-04-17",
      "open": 21.28,
      "close": 21.36,
      "high": 21.66,
      "low": 21.14,
      "volume": 23000566.0,
      "amount": 490765052.0,
      "change_pct": null,
      "turnover": 7.143627881405353,
      "float_market_cap": 6877347167.52,
      "pe_dynamic": 52.43402903
    },
    {
      "date": "2026-04-20",
      "open": 21.57,
      "close": 22.37,
      "high": 23.5,
      "low": 21.55,
      "volume": 61575417.0,
      "amount": 1390406812.0,
      "change_pct": null,
      "turnover": 19.124393099298562,
      "float_market_cap": 7202540081.34,
      "pe_dynamic": 54.91335344
    },
    {
      "date": "2026-04-21",
      "open": 22.53,
      "close": 22.6,
      "high": 22.88,
      "low": 21.68,
      "volume": 42810627.0,
      "amount": 955040027.0,
      "change_pct": null,
      "turnover": 13.296333171003043,
      "float_market_cap": 7276593913.2,
      "pe_dynamic": 55.47795206
    },
    {
      "date": "2026-04-22",
      "open": 22.5,
      "close": 23.19,
      "high": 23.53,
      "low": 22.42,
      "volume": 48647421.0,
      "amount": 1123394556.0,
      "change_pct": null,
      "turnover": 15.109153097104839,
      "float_market_cap": 7466558090.58,
      "pe_dynamic": 56.92627028
    },
    {
      "date": "2026-04-23",
      "open": 22.92,
      "close": 22.46,
      "high": 23.01,
      "low": 21.83,
      "volume": 35790561.0,
      "amount": 799824873.0,
      "change_pct": null,
      "turnover": 11.116006860472002,
      "float_market_cap": 7231517667.72,
      "pe_dynamic": 55.13428333
    },
    {
      "date": "2026-04-24",
      "open": 22.56,
      "close": 22.67,
      "high": 23.27,
      "low": 22.38,
      "volume": 32611993.0,
      "amount": 745298100.0,
      "change_pct": null,
      "turnover": 10.128791720299239,
      "float_market_cap": 7299132035.94,
      "pe_dynamic": 55.64978643
    },
    {
      "date": "2026-04-27",
      "open": 21.5,
      "close": 21.7,
      "high": 21.93,
      "low": 20.43,
      "volume": 36922479.0,
      "amount": 782963732.0,
      "change_pct": null,
      "turnover": 11.467563469307827,
      "float_market_cap": 6986818049.4,
      "pe_dynamic": 80.31464401
    },
    {
      "date": "2026-04-28",
      "open": 21.6,
      "close": 21.11,
      "high": 21.9,
      "low": 20.86,
      "volume": 20543073.0,
      "amount": 434543430.0,
      "change_pct": null,
      "turnover": 6.380367728887433,
      "float_market_cap": 6796853872.02,
      "pe_dynamic": 78.13097397
    },
    {
      "date": "2026-04-29",
      "open": 21.15,
      "close": 23.22,
      "high": 23.22,
      "low": 21.1,
      "volume": 40971926.0,
      "amount": 927320482.0,
      "change_pct": null,
      "turnover": 12.725260453524356,
      "float_market_cap": 7476217286.04,
      "pe_dynamic": 85.94037023
    },
    {
      "date": "2026-04-30",
      "open": 23.4,
      "close": 23.47,
      "high": 23.87,
      "low": 23.05,
      "volume": 47511035.0,
      "amount": 1113985820.0,
      "change_pct": null,
      "turnover": 14.75620879505424,
      "float_market_cap": 7556710581.54,
      "pe_dynamic": 86.86565415
    },
    {
      "date": "2026-05-06",
      "open": 23.48,
      "close": 23.81,
      "high": 23.89,
      "low": 23.07,
      "volume": 41458248.0,
      "amount": 975288719.0,
      "change_pct": null,
      "turnover": 12.87630471037181,
      "float_market_cap": 7666181463.42,
      "pe_dynamic": 88.12404027
    },
    {
      "date": "2026-05-07",
      "open": 23.7,
      "close": 23.67,
      "high": 23.93,
      "low": 23.42,
      "volume": 33396748.0,
      "amount": 789992853.0,
      "change_pct": null,
      "turnover": 10.372524752698192,
      "float_market_cap": 7621105217.94,
      "pe_dynamic": 87.60588128
    },
    {
      "date": "2026-05-08",
      "open": 23.84,
      "close": 23.68,
      "high": 24.48,
      "low": 23.54,
      "volume": 35099685.0,
      "amount": 838831221.0,
      "change_pct": null,
      "turnover": 10.90143122541181,
      "float_market_cap": 7624324949.76,
      "pe_dynamic": 87.64289264
    },
    {
      "date": "2026-05-11",
      "open": 23.89,
      "close": 24.03,
      "high": 24.62,
      "low": 23.75,
      "volume": 39074505.0,
      "amount": 943968291.0,
      "change_pct": null,
      "turnover": 12.135950192274088,
      "float_market_cap": 7737015563.46,
      "pe_dynamic": 88.93829012
    },
    {
      "date": "2026-05-12",
      "open": 24.28,
      "close": 23.25,
      "high": 24.39,
      "low": 23.01,
      "volume": 34113584.0,
      "amount": 800720106.0,
      "change_pct": null,
      "turnover": 10.595163171074292,
      "float_market_cap": 7485876481.5,
      "pe_dynamic": 86.0514043
    },
    {
      "date": "2026-05-13",
      "open": 23.08,
      "close": 24.91,
      "high": 25.2,
      "low": 23.08,
      "volume": 46131599.0,
      "amount": 1133064864.0,
      "change_pct": null,
      "turnover": 14.327776839500874,
      "float_market_cap": 8020351963.62,
      "pe_dynamic": 92.19528951
    },
    {
      "date": "2026-05-14",
      "open": 24.89,
      "close": 24.14,
      "high": 25.34,
      "low": 24.13,
      "volume": 31316423.0,
      "amount": 774953116.0,
      "change_pct": null,
      "turnover": 9.72640727574634,
      "float_market_cap": 7772432613.48,
      "pe_dynamic": 89.34541505
    },
    {
      "date": "2026-05-15",
      "open": 24.5,
      "close": 24.95,
      "high": 25.98,
      "low": 24.38,
      "volume": 40786541.0,
      "amount": 1030958193.0,
      "change_pct": null,
      "turnover": 12.667682676751632,
      "float_market_cap": 8033230890.9,
      "pe_dynamic": 92.34333494
    },
    {
      "date": "2026-05-18",
      "open": 24.99,
      "close": 25.89,
      "high": 26.68,
      "low": 24.58,
      "volume": 40624688.0,
      "amount": 1046965268.0,
      "change_pct": null,
      "turnover": 12.617413583221971,
      "float_market_cap": 8335885681.98,
      "pe_dynamic": 95.82240247
    },
    {
      "date": "2026-05-19",
      "open": 25.58,
      "close": 25.1,
      "high": 25.64,
      "low": 24.39,
      "volume": 31975430.0,
      "amount": 798752079.0,
      "change_pct": null,
      "turnover": 9.931084881473142,
      "float_market_cap": 8081526868.2,
      "pe_dynamic": 92.89850529
    },
    {
      "date": "2026-05-20",
      "open": 24.85,
      "close": 24.37,
      "high": 24.85,
      "low": 23.7,
      "volume": 25469718.0,
      "amount": 617348658.0,
      "change_pct": null,
      "turnover": 7.910509142963342,
      "float_market_cap": 7846486445.34,
      "pe_dynamic": 90.19667625
    },
    {
      "date": "2026-05-21",
      "open": 24.7,
      "close": 24.82,
      "high": 26.81,
      "low": 24.7,
      "volume": 47170860.0,
      "amount": 1222362857.0,
      "change_pct": null,
      "turnover": 14.650555585713345,
      "float_market_cap": 7991374377.24,
      "pe_dynamic": 91.8621873
    },
    {
      "date": "2026-05-22",
      "open": 25.58,
      "close": 26.27,
      "high": 26.66,
      "low": 25.19,
      "volume": 42438813.0,
      "amount": 1103217144.0,
      "change_pct": null,
      "turnover": 13.180853366849664,
      "float_market_cap": 8458235491.14,
      "pe_dynamic": 97.22883402
    },
    {
      "date": "2026-05-25",
      "open": 27.55,
      "close": 27.07,
      "high": 28.09,
      "low": 26.6,
      "volume": 43136557.0,
      "amount": 1177887574.0,
      "change_pct": null,
      "turnover": 13.397562098821014,
      "float_market_cap": 8715814036.74,
      "pe_dynamic": 100.18974255
    },
    {
      "date": "2026-05-26",
      "open": 27.74,
      "close": 29.78,
      "high": 29.78,
      "low": 27.67,
      "volume": 32786633.0,
      "amount": 960371692.0,
      "change_pct": null,
      "turnover": 10.183032262606268,
      "float_market_cap": 9588361359.96,
      "pe_dynamic": 110.21982022
    },
    {
      "date": "2026-05-27",
      "open": 31.3,
      "close": 30.2,
      "high": 32.76,
      "low": 30.01,
      "volume": 77004622.0,
      "amount": 2423313485.0,
      "change_pct": null,
      "turnover": 23.91647078233988,
      "float_market_cap": 9723590096.4,
      "pe_dynamic": 111.7742972
    },
    {
      "date": "2026-05-28",
      "open": 30.05,
      "close": 33.22,
      "high": 33.22,
      "low": 30.0,
      "volume": 63008757.0,
      "amount": 2009530252.0,
      "change_pct": null,
      "turnover": 19.569566821872762,
      "float_market_cap": 10695949106.04,
      "pe_dynamic": 122.95172692
    },
    {
      "date": "2026-05-29",
      "open": 34.22,
      "close": 32.1,
      "high": 34.88,
      "low": 31.9,
      "volume": 63305153.0,
      "amount": 2083060778.0,
      "change_pct": null,
      "turnover": 19.661622936036952,
      "float_market_cap": 10335339142.2,
      "pe_dynamic": 118.80645497
    },
    {
      "date": "2026-06-01",
      "open": 33.9,
      "close": 35.31,
      "high": 35.31,
      "low": 33.71,
      "volume": 15944441.0,
      "amount": 558555791.0,
      "change_pct": null,
      "turnover": 4.952102190920982,
      "float_market_cap": 11368873056.42,
      "pe_dynamic": 130.68710047
    },
    {
      "date": "2026-06-02",
      "open": 35.77,
      "close": 38.84,
      "high": 38.84,
      "low": 35.1,
      "volume": 30604465.0,
      "amount": 1137411913.0,
      "change_pct": null,
      "turnover": 9.505283890383144,
      "float_market_cap": 12505438388.88,
      "pe_dynamic": 143.75210938
    },
    {
      "date": "2026-06-03",
      "open": 42.7,
      "close": 42.72,
      "high": 42.72,
      "low": 41.5,
      "volume": 12994837.0,
      "amount": 552223743.0,
      "change_pct": null,
      "turnover": 4.03599980572295,
      "float_market_cap": 13754694335.04,
      "pe_dynamic": 158.11251577
    },
    {
      "date": "2026-06-04",
      "open": 45.24,
      "close": 46.98,
      "high": 46.98,
      "low": 45.02,
      "volume": 69567763.0,
      "amount": 3226590914.0,
      "change_pct": null,
      "turnover": 21.606694870630562,
      "float_market_cap": 15126300090.36,
      "pe_dynamic": 173.87935372
    },
    {
      "date": "2026-06-05",
      "open": 48.65,
      "close": 49.5,
      "high": 51.68,
      "low": 46.12,
      "volume": 71272468.0,
      "amount": 3554763288.0,
      "change_pct": null,
      "turnover": 22.136150457400518,
      "float_market_cap": 15937672509.0,
      "pe_dynamic": 183.20621561
    },
    {
      "date": "2026-06-08",
      "open": 48.75,
      "close": 52.83,
      "high": 53.99,
      "low": 48.75,
      "volume": 63219878.0,
      "amount": 3284697686.0,
      "change_pct": null,
      "turnover": 19.635137810949733,
      "float_market_cap": 17009843205.06,
      "pe_dynamic": 195.53099738
    },
    {
      "date": "2026-06-09",
      "open": 52.31,
      "close": 55.55,
      "high": 55.58,
      "low": 50.0,
      "volume": 57395625.0,
      "amount": 3018168144.0,
      "change_pct": null,
      "turnover": 17.82621292974643,
      "float_market_cap": 17885610260.1,
      "pe_dynamic": 205.5980864
    },
    {
      "date": "2026-06-10",
      "open": 55.1,
      "close": 58.88,
      "high": 59.08,
      "low": 54.23,
      "volume": 55480267.0,
      "amount": 3185320402.0,
      "change_pct": null,
      "turnover": 17.231331707620296,
      "float_market_cap": 18957780956.16,
      "pe_dynamic": 217.92286818
    },
    {
      "date": "2026-06-11",
      "open": 59.0,
      "close": 54.03,
      "high": 59.01,
      "low": 52.99,
      "volume": 74686779.0,
      "amount": 4145995079.0,
      "change_pct": null,
      "turnover": 23.196583807405425,
      "float_market_cap": 17396211023.46,
      "pe_dynamic": 199.97236019
    },
    {
      "date": "2026-06-12",
      "open": 56.0,
      "close": 53.03,
      "high": 59.0,
      "low": 51.48,
      "volume": 65331499.0,
      "amount": 3545787702.0,
      "change_pct": null,
      "turnover": 20.29097535210246,
      "float_market_cap": 17074237841.46,
      "pe_dynamic": 196.27122452
    },
    {
      "date": "2026-06-15",
      "open": 53.24,
      "close": 53.95,
      "high": 55.73,
      "low": 51.66,
      "volume": 56161063.0,
      "amount": 3040461488.0,
      "change_pct": null,
      "turnover": 17.442776647155664,
      "float_market_cap": 17370453168.9,
      "pe_dynamic": 199.67626933
    },
    {
      "date": "2026-06-16",
      "open": 54.7,
      "close": 56.53,
      "high": 58.6,
      "low": 54.5,
      "volume": 49956341.0,
      "amount": 2835414538.0,
      "change_pct": null,
      "turnover": 15.515683849718886,
      "float_market_cap": 18201143978.46,
      "pe_dynamic": 209.22519936
    },
    {
      "date": "2026-06-17",
      "open": 56.17,
      "close": 57.1,
      "high": 62.18,
      "low": 55.56,
      "volume": 65453482.0,
      "amount": 3826750275.0,
      "change_pct": null,
      "turnover": 20.328861426725904,
      "float_market_cap": 18384668692.2,
      "pe_dynamic": 211.33484669
    },
    {
      "date": "2026-06-18",
      "open": 57.59,
      "close": 56.56,
      "high": 58.8,
      "low": 53.88,
      "volume": 48756928.0,
      "amount": 2753527475.0,
      "change_pct": null,
      "turnover": 15.143164314846569,
      "float_market_cap": 18210803173.92,
      "pe_dynamic": 209.33623343
    },
    {
      "date": "2026-06-22",
      "open": 58.0,
      "close": 62.22,
      "high": 62.22,
      "low": 58.0,
      "volume": 30675719.0,
      "amount": 1861928897.0,
      "change_pct": null,
      "turnover": 9.5274143049591,
      "float_market_cap": 20033171384.04,
      "pe_dynamic": 230.28466131
    },
    {
      "date": "2026-06-23",
      "open": 64.68,
      "close": 56.0,
      "high": 66.39,
      "low": 56.0,
      "volume": 49956531.0,
      "amount": 2939140701.0,
      "change_pct": null,
      "turnover": 15.515742860844849,
      "float_market_cap": 18030498192.0,
      "pe_dynamic": 207.26359745
    },
    {
      "date": "2026-06-24",
      "open": 53.0,
      "close": 51.0,
      "high": 53.98,
      "low": 50.66,
      "volume": 59214832.0,
      "amount": 3061073600.0,
      "change_pct": null,
      "turnover": 18.39123110570122,
      "float_market_cap": 16420632282.0,
      "pe_dynamic": 188.75791911
    },
    {
      "date": "2026-06-25",
      "open": 51.78,
      "close": 52.98,
      "high": 53.38,
      "low": 50.0,
      "volume": 57508646.0,
      "amount": 2983961692.0,
      "change_pct": null,
      "turnover": 17.861315542733617,
      "float_market_cap": 17058139182.36,
      "pe_dynamic": 196.08616773
    },
    {
      "date": "2026-06-26",
      "open": 52.98,
      "close": 58.28,
      "high": 58.28,
      "low": 52.3,
      "volume": 68746906.0,
      "amount": 3941106634.0,
      "change_pct": null,
      "turnover": 21.35174910312872,
      "float_market_cap": 18764597046.96,
      "pe_dynamic": 215.70218678
    },
    {
      "date": "2026-06-29",
      "open": 58.71,
      "close": 57.21,
      "high": 61.68,
      "low": 55.01,
      "volume": 74881345.0,
      "amount": 4406798490.0,
      "change_pct": null,
      "turnover": 23.257013063901702,
      "float_market_cap": 18420085742.22,
      "pe_dynamic": 211.74197161
    },
    {
      "date": "2026-06-30",
      "open": 56.88,
      "close": 62.93,
      "high": 62.93,
      "low": 56.88,
      "volume": 42526598.0,
      "amount": 2600304528.0,
      "change_pct": null,
      "turnover": 13.208118059969355,
      "float_market_cap": 20261772343.26,
      "pe_dynamic": 232.91246764
    }
  ]
}